Json2DbLite/Json2DbLite.py
Json2DbLite/__init__.py
Json2DbLite-1.0.0.dist-info/METADATA
Json2DbLite-1.0.0.dist-info/WHEEL
Json2DbLite-1.0.0.dist-info/top_level.txt
Json2DbLite-1.0.0.dist-info/RECORD
